datasette_visible_internal_db.py
datasette_visible_internal_db-0.1.1.dist-info/METADATA
datasette_visible_internal_db-0.1.1.dist-info/WHEEL
datasette_visible_internal_db-0.1.1.dist-info/entry_points.txt
datasette_visible_internal_db-0.1.1.dist-info/top_level.txt
datasette_visible_internal_db-0.1.1.dist-info/RECORD
