Metadata-Version: 2.1
Name: datasette-visible-internal-db
Version: 0.1.1
Summary: Datasette plugin for making the internal database visible for debugging
Author: Simon Willison
License: Apache-2.0
Project-URL: Homepage, https://github.com/datasette/datasette-visible-internal-db
Project-URL: Changelog, https://github.com/datasette/datasette-visible-internal-db/releases
Project-URL: Issues, https://github.com/datasette/datasette-visible-internal-db/issues
Project-URL: CI, https://github.com/datasette/datasette-visible-internal-db/actions
Classifier: License :: OSI Approved :: Apache Software License
Classifier: Framework :: Datasette
Requires-Dist: datasette >=1.0a5
Provides-Extra: test
Requires-Dist: pytest ; extra == 'test'
Requires-Dist: pytest-asyncio ; extra == 'test'
